README.rst
setup.py
hgwebinit.egg-info/PKG-INFO
hgwebinit.egg-info/SOURCES.txt
hgwebinit.egg-info/dependency_links.txt
hgwebinit.egg-info/top_level.txt
src/__init__.py
src/hgwebinit.py