Metadata-Version: 1.1
Name: hgwebinit
Version: 0.1.0
Summary: Mercurial hgweb init support.
Home-page: https://bitbucket.org/j3hyde/hgwebinit
Author: Jeffrey Kyllo
Author-email: jkyllo@echospiral.com
License: UNKNOWN
Platform: UNKNOWN
Classifier: Development Status :: 1 - Planning
Classifier: Environment :: Plugins
Classifier: Intended Audience :: Developers
Classifier: Intended Audience :: System Administrators
Classifier: License :: OSI Approved :: GNU General Public License v2 or later (GPLv2+)
Classifier: Natural Language :: English
Classifier: Operating System :: OS Independent
Classifier: Programming Language :: Python
Classifier: Topic :: Software Development :: Version Control
